LICENSE.txt
setup.cfg
setup.py
ultimateGZ/Package.py
ultimateGZ/__init__.py
ultimateGZ.egg-info/PKG-INFO
ultimateGZ.egg-info/SOURCES.txt
ultimateGZ.egg-info/dependency_links.txt
ultimateGZ.egg-info/requires.txt
ultimateGZ.egg-info/top_level.txt
ultimateGZ/DATA/100008.jpg
ultimateGZ/DATA/100023.jpg
ultimateGZ/DATA/100053.jpg
ultimateGZ/DATA/100078.jpg
ultimateGZ/DATA/100090.jpg
ultimateGZ/DATA/100122.jpg
ultimateGZ/DATA/100123.jpg
ultimateGZ/DATA/100128.jpg
ultimateGZ/DATA/100134.jpg
ultimateGZ/DATA/100143.jpg
ultimateGZ/DATA/100150.jpg
ultimateGZ/DATA/100157.jpg
ultimateGZ/DATA/100204.jpg
ultimateGZ/DATA/100237.jpg
ultimateGZ/DATA/100259.jpg
ultimateGZ/DATA/100263.jpg
ultimateGZ/DATA/100288.jpg
ultimateGZ/DATA/100295.jpg
ultimateGZ/DATA/100322.jpg
ultimateGZ/DATA/100335.jpg
ultimateGZ/DATA/100380.jpg
ultimateGZ/DATA/100382.jpg
ultimateGZ/DATA/100383.jpg
ultimateGZ/DATA/100402.jpg
ultimateGZ/DATA/100428.jpg
ultimateGZ/DATA/100434.jpg
ultimateGZ/DATA/100444.jpg
ultimateGZ/DATA/100445.jpg
ultimateGZ/DATA/100458.jpg
ultimateGZ/DATA/100474.jpg
ultimateGZ/DATA/100479.jpg
ultimateGZ/DATA/100506.jpg
ultimateGZ/DATA/100513.jpg
ultimateGZ/DATA/100520.jpg
ultimateGZ/DATA/100541.jpg
ultimateGZ/DATA/100561.jpg
ultimateGZ/DATA/100571.jpg
ultimateGZ/DATA/100601.jpg
ultimateGZ/DATA/100623.jpg
ultimateGZ/DATA/100672.jpg
ultimateGZ/DATA/100673.jpg
ultimateGZ/DATA/100724.jpg
ultimateGZ/DATA/100727.jpg
ultimateGZ/DATA/100730.jpg
ultimateGZ/DATA/100740.jpg
ultimateGZ/DATA/100744.jpg
ultimateGZ/DATA/100765.jpg
ultimateGZ/DATA/100774.jpg
ultimateGZ/DATA/100801.jpg
ultimateGZ/DATA/100813.jpg
ultimateGZ/DATA/100821.jpg
ultimateGZ/DATA/100822.jpg
ultimateGZ/DATA/100836.jpg
ultimateGZ/DATA/100852.jpg
ultimateGZ/DATA/100859.jpg
ultimateGZ/DATA/100861.jpg
ultimateGZ/DATA/100867.jpg
ultimateGZ/DATA/100887.jpg
ultimateGZ/DATA/100894.jpg
ultimateGZ/DATA/100938.jpg
ultimateGZ/DATA/100951.jpg
ultimateGZ/DATA/100986.jpg
ultimateGZ/DATA/101007.jpg
ultimateGZ/DATA/101061.jpg
ultimateGZ/DATA/101074.jpg
ultimateGZ/DATA/101092.jpg
ultimateGZ/DATA/101127.jpg
ultimateGZ/DATA/101133.jpg
ultimateGZ/DATA/101135.jpg
ultimateGZ/DATA/101140.jpg
ultimateGZ/DATA/101151.jpg
